yala_events/__init__.py
yala_events/server.py
yala_events-0.1.2.dist-info/METADATA
yala_events-0.1.2.dist-info/WHEEL
yala_events-0.1.2.dist-info/entry_points.txt
yala_events-0.1.2.dist-info/RECORD
