Metadata-Version: 2.4
Name: yala-events
Version: 0.1.2
Summary: A MCP server for Yala Events API
Author-email: Yala Events <hello@yala.events>
Requires-Python: >=3.11
Requires-Dist: httpx>=0.27.0
Requires-Dist: mcp[cli]>=1.5.0
Requires-Dist: python-dotenv>=1.0.0
